{
    "profiles": [
        {
            "name": "yolo_coin",
            "conanFile": "${workspaceFolder}/conanfile.py",
            "profile": "default",
            "installArg": "",
            "buildArg": "",
            "createUser": "disroop",
            "createChannel": "development",
            "createArg": ""
        },
        {
            "name": "yolo_coin-txt",
            "conanFile": "${workspaceFolder}/conanfile.txt",
            "profile": "default",
            "installArg": "",
            "buildArg": "",
            "createUser": "disroop",
            "createChannel": "development",
            "createArg": ""
        }
    ]
}